levanter/__init__.py
levanter/callbacks.py
levanter/checkpoint.py
levanter/config.py
levanter/distributed.py
levanter/grad_accum.py
levanter/logging.py
levanter/lora.py
levanter/mesh.py
levanter/shapes.py
levanter/tensorstore_serialization.py
levanter/trainer.py
levanter/types.py
levanter/visualization.py
levanter/compat/__init__.py
levanter/compat/hf_checkpoints.py
levanter/compat/torch_serialization.py
levanter/config/backpack.yaml
levanter/config/backpack_nano.yaml
levanter/config/gpt2_1536.yaml
levanter/config/gpt2_1536_legal.yaml
levanter/config/gpt2_20b.yaml
levanter/config/gpt2_7b.yaml
levanter/config/gpt2_large.yaml
levanter/config/gpt2_medium.yaml
levanter/config/gpt2_micro.yaml
levanter/config/gpt2_nano.yaml
levanter/config/gpt2_small.yaml
levanter/config/gpt2_small_fast.yaml
levanter/config/gpt2_small_fast_pile.yaml
levanter/config/gpt2_small_local.yaml
levanter/config/gpt2_xl.yaml
levanter/config/lakh_medium.yaml
levanter/config/llama2_7b.yaml
levanter/config/llama2_7b_continued.yaml
levanter/config/llama2_nano.yaml
levanter/config/mpt_7b_continued.yaml
levanter/config/mpt_7b_continued_biomedlm.yaml
levanter/config/data/openwebtext_source.yaml
levanter/config/data/pile_source_old.yaml
levanter/config/data/pubmed_source.yaml
levanter/config/data/redpajama_1b_source.yaml
levanter/config/data/redpajama_1t_source.yaml
levanter/config/data/wikitext_source.yaml
levanter/config/lora/mpt_biomed.yaml
levanter/data/__init__.py
levanter/data/_preprocessor.py
levanter/data/dataset.py
levanter/data/loader.py
levanter/data/shard_cache.py
levanter/data/sharded_dataset.py
levanter/data/text.py
levanter/data/utils.py
levanter/main/cache_dataset.py
levanter/main/eval_lm.py
levanter/main/export_lm_to_hf.py
levanter/main/lora_lm.py
levanter/main/train_lm.py
levanter/main/viz_logprobs.py
levanter/models/__init__.py
levanter/models/attention.py
levanter/models/backpack.py
levanter/models/flash_attention.py
levanter/models/gpt2.py
levanter/models/llama.py
levanter-1.1.dist-info/METADATA
levanter-1.1.dist-info/WHEEL
levanter-1.1.dist-info/licenses/LICENSE
levanter-1.1.dist-info/RECORD
