Metadata-Version: 2.1
Name: levanter
Version: 1.1
Summary: Scalable Training for Foundation Models with Named Tensors and JAX
Project-URL: Homepage, https://github.com/stanford-crfm/levanter
Project-URL: Bug Tracker, https://github.com/stanford-crfm/levanter/issues
Author-email: David Hall <dlwh@cs.stanford.edu>, Ivan Zhou <ivanz@stanford.edu>
License-File: LICENSE
Classifier: Development Status :: 4 - Beta
Classifier: Intended Audience :: Science/Research
Classifier: License :: OSI Approved :: Apache Software License
Classifier: Operating System :: MacOS :: MacOS X
Classifier: Operating System :: POSIX :: Linux
Classifier: Programming Language :: Python :: 3
Requires-Python: >=3.10
Requires-Dist: braceexpand>=0.1.7
Requires-Dist: dataclasses-json
Requires-Dist: datasets==2.11.0
Requires-Dist: draccus>=0.6
Requires-Dist: equinox>=0.10.7
Requires-Dist: fsspec==2023.3.0
Requires-Dist: gcsfs==2023.3.0
Requires-Dist: haliax<2.0,>=1.2
Requires-Dist: humanfriendly==10.0
Requires-Dist: jaxtyping>=0.2.20
Requires-Dist: jmp>=0.0.3
Requires-Dist: matplotlib>=3.7.0
Requires-Dist: optax
Requires-Dist: pyarrow>=11.0.0
Requires-Dist: pydantic<2
Requires-Dist: pytimeparse>=1.1.8
Requires-Dist: ray[default]
Requires-Dist: requests
Requires-Dist: rich>=13
Requires-Dist: safetensors[numpy]
Requires-Dist: tblib<2.0.0,>=1.7.0
Requires-Dist: tensorstore>=0.1.36
Requires-Dist: transformers>=4.22.0
Requires-Dist: wandb
Requires-Dist: zstandard>=0.20.0
